django_force_logout/__init__.py
django_force_logout/app_settings.py
django_force_logout/middleware.py
django_force_logout-3.2.2.dist-info/COPYING
django_force_logout-3.2.2.dist-info/METADATA
django_force_logout-3.2.2.dist-info/WHEEL
django_force_logout-3.2.2.dist-info/top_level.txt
django_force_logout-3.2.2.dist-info/RECORD
