Metadata-Version: 2.1
Name: django-force-logout
Version: 3.2.2
Summary: Framework to be able to forcibly log users out of Django projects
Home-page: https://chris-lamb.co.uk/projects/django-force-logout
Author: Chris Lamb
Author-email: chris@chris-lamb.co.uk
License: BSD
Platform: UNKNOWN
License-File: COPYING
Requires-Dist: Django (>=1.8)
